falcon_crossorigin/__init__.py
falcon_crossorigin/cross_origin.py
falcon_crossorigin/header.py
falcon_crossorigin/method.py
falcon_crossorigin/util.py
falcon_crossorigin-1.0.0.dist-info/LICENSE
falcon_crossorigin-1.0.0.dist-info/METADATA
falcon_crossorigin-1.0.0.dist-info/WHEEL
falcon_crossorigin-1.0.0.dist-info/top_level.txt
falcon_crossorigin-1.0.0.dist-info/RECORD
