Metadata-Version: 2.1
Name: falcon-crossorigin
Version: 1.0.0
Summary: Falcon cross-origin middleware
Home-page: https://github.com/alexferl/falcon-crossorigin
Author: Alexandre Ferland
Author-email: me@alexferl.com
License: MIT
Classifier: Intended Audience :: Developers
Classifier: License :: OSI Approved :: MIT License
Classifier: Operating System :: OS Independent
Classifier: Programming Language :: Python :: 3.8
Classifier: Programming Language :: Python :: 3.9
Classifier: Programming Language :: Python :: 3.10
Classifier: Programming Language :: Python :: 3.11
Classifier: Topic :: Software Development :: Libraries :: Python Modules
Requires-Python: >=3.8
License-File: LICENSE
Requires-Dist: falcon >=2.0.0
